b2bTools/__init__.py
b2bTools/__main__.py
b2bTools/requirements-dev.txt
b2bTools/requirements.txt
b2bTools/web_predictor.py
b2bTools/general/Io.py
b2bTools/general/Util.py
b2bTools/general/__init__.py
b2bTools/general/plotter.py
b2bTools/general/bmrb/File.py
b2bTools/general/bmrb/SaveFrame.py
b2bTools/general/bmrb/TagTable.py
b2bTools/general/bmrb/Text.py
b2bTools/general/bmrb/Utils.py
b2bTools/general/bmrb/__init__.py
b2bTools/general/bmrb/base.py
b2bTools/general/ccpn/__init__.py
b2bTools/general/ccpn/format/__init__.py
b2bTools/general/ccpn/format/general/Constants.py
b2bTools/general/ccpn/format/general/Util.py
b2bTools/general/ccpn/format/general/__init__.py
b2bTools/general/ccpn/format/general/formatIO.py
b2bTools/general/ccpn/format/nmrStar/__init__.py
b2bTools/general/ccpn/format/nmrStar/chemShiftsIO.py
b2bTools/general/ccpn/format/nmrStar/constants.py
b2bTools/general/ccpn/format/nmrStar/coordinatesIO.py
b2bTools/general/ccpn/format/nmrStar/csaIO.py
b2bTools/general/ccpn/format/nmrStar/dihedralConstraintsIO.py
b2bTools/general/ccpn/format/nmrStar/distanceConstraintsIO.py
b2bTools/general/ccpn/format/nmrStar/generalIO.py
b2bTools/general/ccpn/format/nmrStar/hBondConstraintsIO.py
b2bTools/general/ccpn/format/nmrStar/hExchProtectionIO.py
b2bTools/general/ccpn/format/nmrStar/hExchRateIO.py
b2bTools/general/ccpn/format/nmrStar/hetNoeIO.py
b2bTools/general/ccpn/format/nmrStar/jCouplingIO.py
b2bTools/general/ccpn/format/nmrStar/nmrStarDict.py
b2bTools/general/ccpn/format/nmrStar/orderParamIO.py
b2bTools/general/ccpn/format/nmrStar/peopleAndCitationsIO.py
b2bTools/general/ccpn/format/nmrStar/projectIO.py
b2bTools/general/ccpn/format/nmrStar/rdcConstraintsIO.py
b2bTools/general/ccpn/format/nmrStar/rdcIO.py
b2bTools/general/ccpn/format/nmrStar/sequenceIO.py
b2bTools/general/ccpn/format/nmrStar/t1RelaxIO.py
b2bTools/general/ccpn/format/nmrStar/t1RhoRelaxIO.py
b2bTools/general/ccpn/format/nmrStar/t2RelaxIO.py
b2bTools/general/ccpn/format/nmrStar/util.py
b2bTools-3.0.7.dist-info/METADATA
b2bTools-3.0.7.dist-info/WHEEL
b2bTools-3.0.7.dist-info/entry_points.txt
b2bTools-3.0.7.dist-info/top_level.txt
b2bTools-3.0.7.dist-info/RECORD
