Metadata-Version: 2.1
Name: b2bTools
Version: 3.0.7
Summary: bio2Byte software suite to predict protein biophysical properties from their amino-acid sequences
Home-page: https://bio2byte.be
Author: Wim Vranken
Author-email: Wim.Vranken@vub.be
Maintainer: Jose Gavalda-Garcia, Adrian Diaz, Wim Vranken
Maintainer-email: jose.gavalda.garcia@vub.be, adrian.diaz@vub.be, wim.vranken@vub.be
License: OSI Approved :: GNU General Public License v3 (GPLv3)
Project-URL: Documentation, https://bio2byte.be/b2btools/package-documentation
Project-URL: HTML interface, https://bio2byte.be/b2btools
Keywords: bio2byte,b2bTools,biology,bioinformatics,bio-informatics,fasta,proteins,protein-folding
Classifier: Natural Language :: English
Classifier: Programming Language :: Python :: 3.7
Classifier: Programming Language :: Python :: 3.8
Classifier: Programming Language :: Python :: 3.9
Classifier: Programming Language :: Python :: 3.10
Classifier: Programming Language :: Python :: 3.11
Classifier: Programming Language :: Python :: 3.12
Classifier: License :: OSI Approved :: GNU General Public License v3 (GPLv3)
Classifier: Operating System :: MacOS
Classifier: Operating System :: POSIX :: Linux
Classifier: Topic :: Scientific/Engineering :: Bio-Informatics
Classifier: Topic :: Scientific/Engineering :: Chemistry
Classifier: Topic :: Scientific/Engineering :: Physics
Classifier: Intended Audience :: Science/Research
Classifier: Intended Audience :: Education
Classifier: Development Status :: 5 - Production/Stable
Requires-Python: >=3.7, <3.13
Requires-Dist: biopython ~=1.83 ; python_version == "3.10"
Requires-Dist: Cython ~=0.29.37 ; python_version == "3.10"
Requires-Dist: matplotlib ~=3.5.3 ; python_version == "3.10"
Requires-Dist: numpy ~=1.26.4 ; python_version == "3.10"
Requires-Dist: pandas ~=1.5.3 ; python_version == "3.10"
Requires-Dist: pomegranate ~=0.14 ; python_version == "3.10"
Requires-Dist: requests ~=2.31.0 ; python_version == "3.10"
Requires-Dist: scikit-learn ~=1.0.2 ; python_version == "3.10"
Requires-Dist: scipy ~=1.12.0 ; python_version == "3.10"
Requires-Dist: torch ~=1.13.1 ; python_version == "3.10"
Requires-Dist: torchvision ~=0.14.1 ; python_version == "3.10"
Requires-Dist: urllib3 ~=1.26.6 ; python_version == "3.10"
Requires-Dist: biopython ~=1.83 ; python_version == "3.11"
Requires-Dist: matplotlib ~=3.8.3 ; python_version == "3.11"
Requires-Dist: numpy ~=1.26.4 ; python_version == "3.11"
Requires-Dist: pandas ~=1.5.3 ; python_version == "3.11"
Requires-Dist: pomegranate ~=0.14.9 ; python_version == "3.11"
Requires-Dist: requests ~=2.31.0 ; python_version == "3.11"
Requires-Dist: scikit-learn ~=1.4.1.post1 ; python_version == "3.11"
Requires-Dist: scipy ~=1.12.0 ; python_version == "3.11"
Requires-Dist: torch ~=2.2.0 ; python_version == "3.11"
Requires-Dist: urllib3 ~=1.26.18 ; python_version == "3.11"
Requires-Dist: biopython ~=1.83 ; python_version == "3.12"
Requires-Dist: matplotlib ~=3.8.3 ; python_version == "3.12"
Requires-Dist: numpy ~=1.26.4 ; python_version == "3.12"
Requires-Dist: pandas ~=2.1.0 ; python_version == "3.12"
Requires-Dist: pomegranate ~=0.14.9 ; python_version == "3.12"
Requires-Dist: requests ~=2.31.0 ; python_version == "3.12"
Requires-Dist: scikit-learn ~=1.4.1.post1 ; python_version == "3.12"
Requires-Dist: scipy ~=1.12.0 ; python_version == "3.12"
Requires-Dist: torch ~=2.2.0 ; python_version == "3.12"
Requires-Dist: urllib3 ~=1.26.6 ; python_version == "3.12"
Requires-Dist: biopython ~=1.81 ; python_version == "3.7"
Requires-Dist: Cython ~=0.29.37 ; python_version == "3.7"
Requires-Dist: matplotlib ~=3.5.3 ; python_version == "3.7"
Requires-Dist: numpy ~=1.21 ; python_version == "3.7"
Requires-Dist: pandas ~=1.1 ; python_version == "3.7"
Requires-Dist: pomegranate ~=0.14 ; python_version == "3.7"
Requires-Dist: requests ~=2.0 ; python_version == "3.7"
Requires-Dist: scikit-learn ~=1.0.2 ; python_version == "3.7"
Requires-Dist: scipy ==1.7.3 ; python_version == "3.7"
Requires-Dist: torch ==1.11.0 ; python_version == "3.7"
Requires-Dist: urllib3 ~=1.26.6 ; python_version == "3.7"
Requires-Dist: biopython ~=1.81 ; python_version == "3.8"
Requires-Dist: Cython ~=0.29.37 ; python_version == "3.8"
Requires-Dist: matplotlib ~=3.5.3 ; python_version == "3.8"
Requires-Dist: numpy ~=1.24 ; python_version == "3.8"
Requires-Dist: pandas ~=1.1 ; python_version == "3.8"
Requires-Dist: pomegranate ~=0.14 ; python_version == "3.8"
Requires-Dist: requests ~=2.0 ; python_version == "3.8"
Requires-Dist: scikit-learn ~=1.0.2 ; python_version == "3.8"
Requires-Dist: scipy ==1.10.1 ; python_version == "3.8"
Requires-Dist: torch ==1.13.1 ; python_version == "3.8"
Requires-Dist: torchvision ==0.14.1 ; python_version == "3.8"
Requires-Dist: urllib3 ~=1.26.6 ; python_version == "3.8"
Requires-Dist: biopython ~=1.81 ; python_version == "3.9"
Requires-Dist: Cython ~=0.29.37 ; python_version == "3.9"
Requires-Dist: matplotlib ~=3.5.3 ; python_version == "3.9"
Requires-Dist: numpy ~=1.24 ; python_version == "3.9"
Requires-Dist: pandas ~=1.1 ; python_version == "3.9"
Requires-Dist: pomegranate ~=0.14 ; python_version == "3.9"
Requires-Dist: requests ~=2.0 ; python_version == "3.9"
Requires-Dist: scikit-learn ~=1.0.2 ; python_version == "3.9"
Requires-Dist: scipy ==1.10.1 ; python_version == "3.9"
Requires-Dist: torch ==1.13.1 ; python_version == "3.9"
Requires-Dist: torchvision ==0.14.1 ; python_version == "3.9"
Requires-Dist: urllib3 ~=1.26.6 ; python_version == "3.9"
